{
  "number": 1091,
  "type": "Venpa",
  "tamil_type": "வெண்பா",
  "status": "success",
  "value": "இருநோக் கிவளுண்க ணுள்ள தொருநோக்கு\nநோய்நோக்கொன் றந்நோய் மருந்து",
  "errors": [],
  "structure": [
    {
      "type": "Adi",
      "tamil_type": "அடி",
      "value": "இருநோக் கிவளுண்க ணுள்ள தொருநோக்கு",
      "feet": [
        {
          "type": "Cheer",
          "tamil_type": "சீர்",
          "value": "இருநோக்",
          "children": [
            {
              "type": "Pulima",
              "tamil_type": "புளிமா",
              "value": "இருநோக்",
              "children": [
                {
                  "type": "Nirai",
                  "tamil_type": "நிரை",
                  "value": "இரு",
                  "children": [
                    {
                      "type": "Kuril",
                      "tamil_type": "குறில்",
                      "value": "இ"
                    },
                    {
                      "type": "Mutriyalugaram",
                      "tamil_type": "முற்றியலுகரம்",
                      "value": "ரு"
                    }
                  ]
                },
                {
                  "type": "Ner",
                  "tamil_type": "நேர்",
                  "value": "நோக்",
                  "children": [
                    {
                      "type": "Nedil",
                      "tamil_type": "நெடில்",
                      "value": "நோ"
                    },
                    {
                      "type": "Otru",
                      "tamil_type": "ஒற்று",
                      "value": "க்"
                    }
                  ]
                }
              ]
            }
          ]
        },
        {
          "type": "Cheer",
          "tamil_type": "சீர்",
          "value": "கிவளுண்க",
          "children": [
            {
              "type": "Pulimangai",
              "tamil_type": "புளிமாங்காய்",
              "value": "கிவளுண்க",
              "children": [
                {
                  "type": "Pulima",
                  "tamil_type": "புளிமா",
                  "value": "கிவளுண்",
                  "children": [
                    {
                      "type": "Nirai",
                      "tamil_type": "நிரை",
                      "value": "கிவ",
                      "children": [
                        {
                          "type": "Kuril",
                          "tamil_type": "குறில்",
                          "value": "கி"
                        },
                        {
                          "type": "Kuril",
                          "tamil_type": "குறில்",
                          "value": "வ"
                        }
                      ]
                    },
                    {
                      "type": "Ner",
                      "tamil_type": "நேர்",
                      "value": "ளுண்",
                      "children": [
                        {
                          "type": "Mutriyalugaram",
                          "tamil_type": "முற்றியலுகரம்",
                          "value": "ளு"
                        },
                        {
                          "type": "Otru",
                          "tamil_type": "ஒற்று",
                          "value": "ண்"
                        }
                      ]
                    }
                  ]
                },
                {
                  "type": "Ner",
                  "tamil_type": "நேர்",
                  "value": "க",
                  "children": [
                    {
                      "type": "Kuril",
                      "tamil_type": "குறில்",
                      "value": "க"
                    }
                  ]
                }
              ]
            }
          ]
        },
        {
          "type": "Cheer",
          "tamil_type": "சீர்",
          "value": "ணுள்ள",
          "children": [
            {
              "type": "Thema",
              "tamil_type": "தேமா",
              "value": "ணுள்ள",
              "children": [
                {
                  "type": "Ner",
                  "tamil_type": "நேர்",
                  "value": "ணுள்",
                  "children": [
                    {
                      "type": "Mutriyalugaram",
                      "tamil_type": "முற்றியலுகரம்",
                      "value": "ணு"
                    },
                    {
                      "type": "Otru",
                      "tamil_type": "ஒற்று",
                      "value": "ள்"
                    }
                  ]
                },
                {
                  "type": "Ner",
                  "tamil_type": "நேர்",
                  "value": "ள",
                  "children": [
                    {
                      "type": "Kuril",
                      "tamil_type": "குறில்",
                      "value": "ள"
                    }
                  ]
                }
              ]
            }
          ]
        },
        {
          "type": "Cheer",
          "tamil_type": "சீர்",
          "value": "தொருநோக்கு",
          "children": [
            {
              "type": "Pulimangai",
              "tamil_type": "புளிமாங்காய்",
              "value": "தொருநோக்கு",
              "children": [
                {
                  "type": "Pulima",
                  "tamil_type": "புளிமா",
                  "value": "தொருநோக்",
                  "children": [
                    {
                      "type": "Nirai",
                      "tamil_type": "நிரை",
                      "value": "தொரு",
                      "children": [
                        {
                          "type": "Kuril",
                          "tamil_type": "குறில்",
                          "value": "தொ"
                        },
                        {
                          "type": "Mutriyalugaram",
                          "tamil_type": "முற்றியலுகரம்",
                          "value": "ரு"
                        }
                      ]
                    },
                    {
                      "type": "Ner",
                      "tamil_type": "நேர்",
                      "value": "நோக்",
                      "children": [
                        {
                          "type": "Nedil",
                          "tamil_type": "நெடில்",
                          "value": "நோ"
                        },
                        {
                          "type": "Otru",
                          "tamil_type": "ஒற்று",
                          "value": "க்"
                        }
                      ]
                    }
                  ]
                },
                {
                  "type": "Ner",
                  "tamil_type": "நேர்",
                  "value": "கு",
                  "children": [
                    {
                      "type": "Kutriyalugaram",
                      "tamil_type": "குற்றியலுகரம்",
                      "value": "கு"
                    }
                  ]
                }
              ]
            }
          ]
        }
      ]
    },
    {
      "type": "Eetradi",
      "tamil_type": "ஈற்றடி",
      "value": "நோய்நோக்கொன் றந்நோய் மருந்து",
      "feet": [
        {
          "type": "Cheer",
          "tamil_type": "சீர்",
          "value": "நோய்நோக்கொன்",
          "children": [
            {
              "type": "Themangai",
              "tamil_type": "தேமாங்காய்",
              "value": "நோய்நோக்கொன்",
              "children": [
                {
                  "type": "Thema",
                  "tamil_type": "தேமா",
                  "value": "நோய்நோக்",
                  "children": [
                    {
                      "type": "Ner",
                      "tamil_type": "நேர்",
                      "value": "நோய்",
                      "children": [
                        {
                          "type": "Nedil",
                          "tamil_type": "நெடில்",
                          "value": "நோ"
                        },
                        {
                          "type": "Otru",
                          "tamil_type": "ஒற்று",
                          "value": "ய்"
                        }
                      ]
                    },
                    {
                      "type": "Ner",
                      "tamil_type": "நேர்",
                      "value": "நோக்",
                      "children": [
                        {
                          "type": "Nedil",
                          "tamil_type": "நெடில்",
                          "value": "நோ"
                        },
                        {
                          "type": "Otru",
                          "tamil_type": "ஒற்று",
                          "value": "க்"
                        }
                      ]
                    }
                  ]
                },
                {
                  "type": "Ner",
                  "tamil_type": "நேர்",
                  "value": "கொன்",
                  "children": [
                    {
                      "type": "Kuril",
                      "tamil_type": "குறில்",
                      "value": "கொ"
                    },
                    {
                      "type": "Otru",
                      "tamil_type": "ஒற்று",
                      "value": "ன்"
                    }
                  ]
                }
              ]
            }
          ]
        },
        {
          "type": "Cheer",
          "tamil_type": "சீர்",
          "value": "றந்நோய்",
          "children": [
            {
              "type": "Thema",
              "tamil_type": "தேமா",
              "value": "றந்நோய்",
              "children": [
                {
                  "type": "Ner",
                  "tamil_type": "நேர்",
                  "value": "றந்",
                  "children": [
                    {
                      "type": "Kuril",
                      "tamil_type": "குறில்",
                      "value": "ற"
                    },
                    {
                      "type": "Otru",
                      "tamil_type": "ஒற்று",
                      "value": "ந்"
                    }
                  ]
                },
                {
                  "type": "Ner",
                  "tamil_type": "நேர்",
                  "value": "நோய்",
                  "children": [
                    {
                      "type": "Nedil",
                      "tamil_type": "நெடில்",
                      "value": "நோ"
                    },
                    {
                      "type": "Otru",
                      "tamil_type": "ஒற்று",
                      "value": "ய்"
                    }
                  ]
                }
              ]
            }
          ]
        },
        {
          "type": "EetruCheer",
          "tamil_type": "ஈற்றுச்சீர்",
          "value": "மருந்து",
          "children": [
            {
              "type": "Pirappu",
              "tamil_type": "பிறப்பு",
              "value": "மருந்து",
              "children": [
                {
                  "type": "Nirai",
                  "tamil_type": "நிரை",
                  "value": "மருந்",
                  "children": [
                    {
                      "type": "Kuril",
                      "tamil_type": "குறில்",
                      "value": "ம"
                    },
                    {
                      "type": "Mutriyalugaram",
                      "tamil_type": "முற்றியலுகரம்",
                      "value": "ரு"
                    },
                    {
                      "type": "Otru",
                      "tamil_type": "ஒற்று",
                      "value": "ந்"
                    }
                  ]
                },
                {
                  "type": "Ner",
                  "tamil_type": "நேர்",
                  "value": "து",
                  "children": [
                    {
                      "type": "Kutriyalugaram",
                      "tamil_type": "குற்றியலுகரம்",
                      "value": "து"
                    }
                  ]
                }
              ]
            }
          ]
        }
      ]
    }
  ]
}