{
  "number": 535,
  "type": "Venpa",
  "tamil_type": "வெண்பா",
  "status": "success",
  "value": "முன்னுறக் காவா திழுக்கியான் றன்பிழை\nபின்னூ றிரங்கி விடும்",
  "errors": [],
  "structure": [
    {
      "type": "Adi",
      "tamil_type": "அடி",
      "value": "முன்னுறக் காவா திழுக்கியான் றன்பிழை",
      "feet": [
        {
          "type": "Cheer",
          "tamil_type": "சீர்",
          "value": "முன்னுறக்",
          "children": [
            {
              "type": "Koovilam",
              "tamil_type": "கூவிளம்",
              "value": "முன்னுறக்",
              "children": [
                {
                  "type": "Ner",
                  "tamil_type": "நேர்",
                  "value": "முன்",
                  "children": [
                    {
                      "type": "Mutriyalugaram",
                      "tamil_type": "முற்றியலுகரம்",
                      "value": "மு"
                    },
                    {
                      "type": "Otru",
                      "tamil_type": "ஒற்று",
                      "value": "ன்"
                    }
                  ]
                },
                {
                  "type": "Nirai",
                  "tamil_type": "நிரை",
                  "value": "னுறக்",
                  "children": [
                    {
                      "type": "Mutriyalugaram",
                      "tamil_type": "முற்றியலுகரம்",
                      "value": "னு"
                    },
                    {
                      "type": "Kuril",
                      "tamil_type": "குறில்",
                      "value": "ற"
                    },
                    {
                      "type": "Otru",
                      "tamil_type": "ஒற்று",
                      "value": "க்"
                    }
                  ]
                }
              ]
            }
          ]
        },
        {
          "type": "Cheer",
          "tamil_type": "சீர்",
          "value": "காவா",
          "children": [
            {
              "type": "Thema",
              "tamil_type": "தேமா",
              "value": "காவா",
              "children": [
                {
                  "type": "Ner",
                  "tamil_type": "நேர்",
                  "value": "கா",
                  "children": [
                    {
                      "type": "Nedil",
                      "tamil_type": "நெடில்",
                      "value": "கா"
                    }
                  ]
                },
                {
                  "type": "Ner",
                  "tamil_type": "நேர்",
                  "value": "வா",
                  "children": [
                    {
                      "type": "Nedil",
                      "tamil_type": "நெடில்",
                      "value": "வா"
                    }
                  ]
                }
              ]
            }
          ]
        },
        {
          "type": "Cheer",
          "tamil_type": "சீர்",
          "value": "திழுக்கியான்",
          "children": [
            {
              "type": "Karuvilam",
              "tamil_type": "கருவிளம்",
              "value": "திழுக்கியான்",
              "children": [
                {
                  "type": "Nirai",
                  "tamil_type": "நிரை",
                  "value": "திழுக்",
                  "children": [
                    {
                      "type": "Kuril",
                      "tamil_type": "குறில்",
                      "value": "தி"
                    },
                    {
                      "type": "Mutriyalugaram",
                      "tamil_type": "முற்றியலுகரம்",
                      "value": "ழு"
                    },
                    {
                      "type": "Otru",
                      "tamil_type": "ஒற்று",
                      "value": "க்"
                    }
                  ]
                },
                {
                  "type": "Nirai",
                  "tamil_type": "நிரை",
                  "value": "கியான்",
                  "children": [
                    {
                      "type": "Kuril",
                      "tamil_type": "குறில்",
                      "value": "கி"
                    },
                    {
                      "type": "Nedil",
                      "tamil_type": "நெடில்",
                      "value": "யா"
                    },
                    {
                      "type": "Otru",
                      "tamil_type": "ஒற்று",
                      "value": "ன்"
                    }
                  ]
                }
              ]
            }
          ]
        },
        {
          "type": "Cheer",
          "tamil_type": "சீர்",
          "value": "றன்பிழை",
          "children": [
            {
              "type": "Koovilam",
              "tamil_type": "கூவிளம்",
              "value": "றன்பிழை",
              "children": [
                {
                  "type": "Ner",
                  "tamil_type": "நேர்",
                  "value": "றன்",
                  "children": [
                    {
                      "type": "Kuril",
                      "tamil_type": "குறில்",
                      "value": "ற"
                    },
                    {
                      "type": "Otru",
                      "tamil_type": "ஒற்று",
                      "value": "ன்"
                    }
                  ]
                },
                {
                  "type": "Nirai",
                  "tamil_type": "நிரை",
                  "value": "பிழை",
                  "children": [
                    {
                      "type": "Kuril",
                      "tamil_type": "குறில்",
                      "value": "பி"
                    },
                    {
                      "type": "Nedil",
                      "tamil_type": "நெடில்",
                      "value": "ழை"
                    }
                  ]
                }
              ]
            }
          ]
        }
      ]
    },
    {
      "type": "Eetradi",
      "tamil_type": "ஈற்றடி",
      "value": "பின்னூ றிரங்கி விடும்",
      "feet": [
        {
          "type": "Cheer",
          "tamil_type": "சீர்",
          "value": "பின்னூ",
          "children": [
            {
              "type": "Thema",
              "tamil_type": "தேமா",
              "value": "பின்னூ",
              "children": [
                {
                  "type": "Ner",
                  "tamil_type": "நேர்",
                  "value": "பின்",
                  "children": [
                    {
                      "type": "Kuril",
                      "tamil_type": "குறில்",
                      "value": "பி"
                    },
                    {
                      "type": "Otru",
                      "tamil_type": "ஒற்று",
                      "value": "ன்"
                    }
                  ]
                },
                {
                  "type": "Ner",
                  "tamil_type": "நேர்",
                  "value": "னூ",
                  "children": [
                    {
                      "type": "Nedil",
                      "tamil_type": "நெடில்",
                      "value": "னூ"
                    }
                  ]
                }
              ]
            }
          ]
        },
        {
          "type": "Cheer",
          "tamil_type": "சீர்",
          "value": "றிரங்கி",
          "children": [
            {
              "type": "Pulima",
              "tamil_type": "புளிமா",
              "value": "றிரங்கி",
              "children": [
                {
                  "type": "Nirai",
                  "tamil_type": "நிரை",
                  "value": "றிரங்",
                  "children": [
                    {
                      "type": "Kuril",
                      "tamil_type": "குறில்",
                      "value": "றி"
                    },
                    {
                      "type": "Kuril",
                      "tamil_type": "குறில்",
                      "value": "ர"
                    },
                    {
                      "type": "Otru",
                      "tamil_type": "ஒற்று",
                      "value": "ங்"
                    }
                  ]
                },
                {
                  "type": "Ner",
                  "tamil_type": "நேர்",
                  "value": "கி",
                  "children": [
                    {
                      "type": "Kuril",
                      "tamil_type": "குறில்",
                      "value": "கி"
                    }
                  ]
                }
              ]
            }
          ]
        },
        {
          "type": "EetruCheer",
          "tamil_type": "ஈற்றுச்சீர்",
          "value": "விடும்",
          "children": [
            {
              "type": "Malar",
              "tamil_type": "மலர்",
              "value": "விடும்",
              "children": [
                {
                  "type": "Nirai",
                  "tamil_type": "நிரை",
                  "value": "விடும்",
                  "children": [
                    {
                      "type": "Kuril",
                      "tamil_type": "குறில்",
                      "value": "வி"
                    },
                    {
                      "type": "Kutriyalugaram",
                      "tamil_type": "குற்றியலுகரம்",
                      "value": "டு"
                    },
                    {
                      "type": "Otru",
                      "tamil_type": "ஒற்று",
                      "value": "ம்"
                    }
                  ]
                }
              ]
            }
          ]
        }
      ]
    }
  ]
}