{
  "number": 811,
  "type": "Venpa",
  "tamil_type": "வெண்பா",
  "status": "success",
  "value": "பருகுவார் போலினும் பண்பிலார் கேண்மை\nபெருகலிற் குன்ற லினிது",
  "errors": [],
  "structure": [
    {
      "type": "Adi",
      "tamil_type": "அடி",
      "value": "பருகுவார் போலினும் பண்பிலார் கேண்மை",
      "feet": [
        {
          "type": "Cheer",
          "tamil_type": "சீர்",
          "value": "பருகுவார்",
          "children": [
            {
              "type": "Karuvilam",
              "tamil_type": "கருவிளம்",
              "value": "பருகுவார்",
              "children": [
                {
                  "type": "Nirai",
                  "tamil_type": "நிரை",
                  "value": "பரு",
                  "children": [
                    {
                      "type": "Kuril",
                      "tamil_type": "குறில்",
                      "value": "ப"
                    },
                    {
                      "type": "Mutriyalugaram",
                      "tamil_type": "முற்றியலுகரம்",
                      "value": "ரு"
                    }
                  ]
                },
                {
                  "type": "Nirai",
                  "tamil_type": "நிரை",
                  "value": "குவார்",
                  "children": [
                    {
                      "type": "Kutriyalugaram",
                      "tamil_type": "குற்றியலுகரம்",
                      "value": "கு"
                    },
                    {
                      "type": "Nedil",
                      "tamil_type": "நெடில்",
                      "value": "வா"
                    },
                    {
                      "type": "Otru",
                      "tamil_type": "ஒற்று",
                      "value": "ர்"
                    }
                  ]
                }
              ]
            }
          ]
        },
        {
          "type": "Cheer",
          "tamil_type": "சீர்",
          "value": "போலினும்",
          "children": [
            {
              "type": "Koovilam",
              "tamil_type": "கூவிளம்",
              "value": "போலினும்",
              "children": [
                {
                  "type": "Ner",
                  "tamil_type": "நேர்",
                  "value": "போ",
                  "children": [
                    {
                      "type": "Nedil",
                      "tamil_type": "நெடில்",
                      "value": "போ"
                    }
                  ]
                },
                {
                  "type": "Nirai",
                  "tamil_type": "நிரை",
                  "value": "லினும்",
                  "children": [
                    {
                      "type": "Kuril",
                      "tamil_type": "குறில்",
                      "value": "லி"
                    },
                    {
                      "type": "Mutriyalugaram",
                      "tamil_type": "முற்றியலுகரம்",
                      "value": "னு"
                    },
                    {
                      "type": "Otru",
                      "tamil_type": "ஒற்று",
                      "value": "ம்"
                    }
                  ]
                }
              ]
            }
          ]
        },
        {
          "type": "Cheer",
          "tamil_type": "சீர்",
          "value": "பண்பிலார்",
          "children": [
            {
              "type": "Koovilam",
              "tamil_type": "கூவிளம்",
              "value": "பண்பிலார்",
              "children": [
                {
                  "type": "Ner",
                  "tamil_type": "நேர்",
                  "value": "பண்",
                  "children": [
                    {
                      "type": "Kuril",
                      "tamil_type": "குறில்",
                      "value": "ப"
                    },
                    {
                      "type": "Otru",
                      "tamil_type": "ஒற்று",
                      "value": "ண்"
                    }
                  ]
                },
                {
                  "type": "Nirai",
                  "tamil_type": "நிரை",
                  "value": "பிலார்",
                  "children": [
                    {
                      "type": "Kuril",
                      "tamil_type": "குறில்",
                      "value": "பி"
                    },
                    {
                      "type": "Nedil",
                      "tamil_type": "நெடில்",
                      "value": "லா"
                    },
                    {
                      "type": "Otru",
                      "tamil_type": "ஒற்று",
                      "value": "ர்"
                    }
                  ]
                }
              ]
            }
          ]
        },
        {
          "type": "Cheer",
          "tamil_type": "சீர்",
          "value": "கேண்மை",
          "children": [
            {
              "type": "Thema",
              "tamil_type": "தேமா",
              "value": "கேண்மை",
              "children": [
                {
                  "type": "Ner",
                  "tamil_type": "நேர்",
                  "value": "கேண்",
                  "children": [
                    {
                      "type": "Nedil",
                      "tamil_type": "நெடில்",
                      "value": "கே"
                    },
                    {
                      "type": "Otru",
                      "tamil_type": "ஒற்று",
                      "value": "ண்"
                    }
                  ]
                },
                {
                  "type": "Ner",
                  "tamil_type": "நேர்",
                  "value": "மை",
                  "children": [
                    {
                      "type": "Nedil",
                      "tamil_type": "நெடில்",
                      "value": "மை"
                    }
                  ]
                }
              ]
            }
          ]
        }
      ]
    },
    {
      "type": "Eetradi",
      "tamil_type": "ஈற்றடி",
      "value": "பெருகலிற் குன்ற லினிது",
      "feet": [
        {
          "type": "Cheer",
          "tamil_type": "சீர்",
          "value": "பெருகலிற்",
          "children": [
            {
              "type": "Karuvilam",
              "tamil_type": "கருவிளம்",
              "value": "பெருகலிற்",
              "children": [
                {
                  "type": "Nirai",
                  "tamil_type": "நிரை",
                  "value": "பெரு",
                  "children": [
                    {
                      "type": "Kuril",
                      "tamil_type": "குறில்",
                      "value": "பெ"
                    },
                    {
                      "type": "Mutriyalugaram",
                      "tamil_type": "முற்றியலுகரம்",
                      "value": "ரு"
                    }
                  ]
                },
                {
                  "type": "Nirai",
                  "tamil_type": "நிரை",
                  "value": "கலிற்",
                  "children": [
                    {
                      "type": "Kuril",
                      "tamil_type": "குறில்",
                      "value": "க"
                    },
                    {
                      "type": "Kuril",
                      "tamil_type": "குறில்",
                      "value": "லி"
                    },
                    {
                      "type": "Otru",
                      "tamil_type": "ஒற்று",
                      "value": "ற்"
                    }
                  ]
                }
              ]
            }
          ]
        },
        {
          "type": "Cheer",
          "tamil_type": "சீர்",
          "value": "குன்ற",
          "children": [
            {
              "type": "Thema",
              "tamil_type": "தேமா",
              "value": "குன்ற",
              "children": [
                {
                  "type": "Ner",
                  "tamil_type": "நேர்",
                  "value": "குன்",
                  "children": [
                    {
                      "type": "Kutriyalugaram",
                      "tamil_type": "குற்றியலுகரம்",
                      "value": "கு"
                    },
                    {
                      "type": "Otru",
                      "tamil_type": "ஒற்று",
                      "value": "ன்"
                    }
                  ]
                },
                {
                  "type": "Ner",
                  "tamil_type": "நேர்",
                  "value": "ற",
                  "children": [
                    {
                      "type": "Kuril",
                      "tamil_type": "குறில்",
                      "value": "ற"
                    }
                  ]
                }
              ]
            }
          ]
        },
        {
          "type": "EetruCheer",
          "tamil_type": "ஈற்றுச்சீர்",
          "value": "லினிது",
          "children": [
            {
              "type": "Pirappu",
              "tamil_type": "பிறப்பு",
              "value": "லினிது",
              "children": [
                {
                  "type": "Nirai",
                  "tamil_type": "நிரை",
                  "value": "லினி",
                  "children": [
                    {
                      "type": "Kuril",
                      "tamil_type": "குறில்",
                      "value": "லி"
                    },
                    {
                      "type": "Kuril",
                      "tamil_type": "குறில்",
                      "value": "னி"
                    }
                  ]
                },
                {
                  "type": "Ner",
                  "tamil_type": "நேர்",
                  "value": "து",
                  "children": [
                    {
                      "type": "Kutriyalugaram",
                      "tamil_type": "குற்றியலுகரம்",
                      "value": "து"
                    }
                  ]
                }
              ]
            }
          ]
        }
      ]
    }
  ]
}